lazydf/__init__.py
lazydf/compression.py
lazydf-0.220726.3.dist-info/LICENSE
lazydf-0.220726.3.dist-info/METADATA
lazydf-0.220726.3.dist-info/WHEEL
lazydf-0.220726.3.dist-info/RECORD
