Metadata-Version: 2.1
Name: lazydf
Version: 0.220726.3
Summary: Hopefully safe and deterministic serializer to binary format, including Pandas data
License: GPL
Author: davips
Author-email: dpsabc@gmail.com
Requires-Python: >=3.10,<4.0
Classifier: License :: Other/Proprietary License
Classifier: Programming Language :: Python :: 3
Classifier: Programming Language :: Python :: 3.10
Classifier: Programming Language :: Python :: 3.11
Requires-Dist: orjson (>=3.7.8,<4.0.0)
Requires-Dist: pymongo (>=4.2.0,<5.0.0)
